PieData/__init__.py
PieData/cli.py
PieData/main.py
PieData/server.py
piedata-0.1.0.dist-info/METADATA
piedata-0.1.0.dist-info/WHEEL
piedata-0.1.0.dist-info/entry_points.txt
piedata-0.1.0.dist-info/licenses/LICENSE
piedata-0.1.0.dist-info/RECORD
