Metadata-Version: 2.4
Name: PieData
Version: 0.1.0
Summary:  PieData is a database based on separate files.
Project-URL: Homepage, https://github.com/Library-Keeper/PieData
Project-URL: Issues, https://github.com/Library-Keeper/PieData/issues
Project-URL: Documentation, https://github.com/Library-Keeper/PieData/wiki
Author: Library_Keeper
License: MIT
License-File: LICENSE
Keywords: database,files,piedata
Classifier: Development Status :: 3 - Alpha
Classifier: Intended Audience :: Education
Classifier: License :: OSI Approved :: MIT License
Classifier: Operating System :: OS Independent
Classifier: Programming Language :: Python :: 3.13
Requires-Python: >=3.13
Requires-Dist: websockets==14.2
